lxmfy_js8call_bot/__init__.py
lxmfy_js8call_bot/bot.py
lxmfy_js8call_bot/storage/__init__.py
lxmfy_js8call_bot/storage/sqlite_storage.py
lxmfy_js8call_bot-1.0.0.dist-info/METADATA
lxmfy_js8call_bot-1.0.0.dist-info/WHEEL
lxmfy_js8call_bot-1.0.0.dist-info/entry_points.txt
lxmfy_js8call_bot-1.0.0.dist-info/licenses/LICENSE
lxmfy_js8call_bot-1.0.0.dist-info/RECORD
