Metadata-Version: 2.4
Name: lxmfy-js8call-bot
Version: 1.0.0
Summary: A JS8Call RX-Only Bot
License-File: LICENSE
Author: LXMFy
Requires-Python: >=3.11
Classifier: Programming Language :: Python :: 3
Classifier: Programming Language :: Python :: 3.11
Classifier: Programming Language :: Python :: 3.12
Classifier: Programming Language :: Python :: 3.13
Classifier: Programming Language :: Python :: 3.14
Requires-Dist: lxmfy (>=1.0.3)
